<?xml version="1.0" encoding="UTF-8"?>

<!-- generated on Thu  8 Apr 13:36:01 2021 by Eclipse SUMO GUI Version 1.8.0
<configuration xmlns:xsi="http://www.w3.org/2001/XMLSchema-instance" xsi:noNamespaceSchemaLocation="http://sumo.dlr.de/xsd/sumoConfiguration.xsd">

    <input>
        <net-file value="network/simpleMap.net.xml"/>
        <route-files value="network/routes.rou.xml"/>
        <additional-files value="network/add_macro.xml"/>
    </input>

    <output>
        <queue-output value="network/queuedata.xml"/>
    </output>

    <processing>
        <time-to-teleport value="-1"/>
        <waiting-time-memory value="5400"/>
    </processing>

    <report>
        <no-step-log value="true"/>
    </report>

    <traci_server>
        <remote-port value="55018"/>
    </traci_server>

</configuration>
-->

<meandata xmlns:xsi="http://www.w3.org/2001/XMLSchema-instance" xsi:noNamespaceSchemaLocation="http://sumo.dlr.de/xsd/meandata_file.xsd">
    <interval begin="0.00" end="5400.00" id="info">
        <edge id="E2T">
            <lane id="E2T_0" sampledSeconds="141096.12" traveltime="1228.78" overlapTraveltime="1233.25" density="107.61" laneDensity="107.61" occupancy="53.78" waitingTime="124377.00" timeLoss="139078.42" speed="0.20" departed="131" arrived="0" entered="0" left="101" laneChangedFrom="0" laneChangedTo="0"/>
        </edge>
        <edge id="N2T">
            <lane id="N2T_0" sampledSeconds="23407.10" traveltime="98.91" overlapTraveltime="100.00" density="17.85" laneDensity="17.85" occupancy="8.88" waitingTime="14705.00" timeLoss="19110.27" speed="2.48" departed="239" arrived="0" entered="0" left="239" laneChangedFrom="0" laneChangedTo="0"/>
        </edge>
        <edge id="S2T">
            <lane id="S2T_0" sampledSeconds="144064.05" traveltime="1687.13" overlapTraveltime="1694.33" density="109.88" laneDensity="109.88" occupancy="54.92" waitingTime="130795.00" timeLoss="142540.54" speed="0.15" departed="101" arrived="0" entered="0" left="71" laneChangedFrom="0" laneChangedTo="0"/>
        </edge>
        <edge id="T2E">
            <lane id="T2E_0" sampledSeconds="4171.87" traveltime="21.20" overlapTraveltime="21.58" density="3.18" laneDensity="3.18" occupancy="1.55" waitingTime="0.00" timeLoss="702.21" speed="11.48" departed="0" arrived="194" entered="194" left="0" laneChangedFrom="0" laneChangedTo="0"/>
        </edge>
        <edge id="T2N">
            <lane id="T2N_0" sampledSeconds="1950.07" traveltime="21.38" overlapTraveltime="21.77" density="1.49" laneDensity="1.49" occupancy="0.72" waitingTime="0.00" timeLoss="351.15" speed="11.38" departed="0" arrived="90" entered="90" left="0" laneChangedFrom="0" laneChangedTo="0"/>
        </edge>
        <edge id="T2S">
            <lane id="T2S_0" sampledSeconds="4087.83" traveltime="20.67" overlapTraveltime="21.05" density="3.12" laneDensity="3.12" occupancy="1.52" waitingTime="0.00" timeLoss="578.37" speed="11.77" departed="0" arrived="195" entered="195" left="0" laneChangedFrom="0" laneChangedTo="0"/>
        </edge>
        <edge id="T2W">
            <lane id="T2W_0" sampledSeconds="2595.91" traveltime="20.81" overlapTraveltime="21.19" density="1.98" laneDensity="1.98" occupancy="0.96" waitingTime="0.00" timeLoss="429.76" speed="11.70" departed="0" arrived="123" entered="123" left="0" laneChangedFrom="0" laneChangedTo="0"/>
        </edge>
        <edge id="W2T">
            <lane id="W2T_0" sampledSeconds="133864.16" traveltime="658.70" overlapTraveltime="660.87" density="102.10" laneDensity="102.10" occupancy="51.00" waitingTime="109396.00" timeLoss="130231.22" speed="0.37" departed="221" arrived="0" entered="0" left="191" laneChangedFrom="0" laneChangedTo="0"/>
        </edge>
    </interval>
</meandata>
